ascalculator/__init__.py
ascalculator/calculator.py
ascalculator-0.0.2.dist-info/METADATA
ascalculator-0.0.2.dist-info/WHEEL
ascalculator-0.0.2.dist-info/license
ascalculator-0.0.2.dist-info/top_level.txt
ascalculator-0.0.2.dist-info/RECORD
