Metadata-Version: 2.1
Name: ascalculator
Version: 0.0.2
Summary: This is a very basic calculator and i am just trying to upload it, nothing more.....
Home-page: UNKNOWN
Author: Abid Sahariar Sanjid
Author-email: 1001128@daffodil.ac
License: UNKNOWN
Platform: UNKNOWN
License-File: license
